cryptshield/__init__.py
cryptshield/cryptshield.py
cryptshield/metadata_cleaner.py
cryptshield-1.1.1.dist-info/licenses/LICENSE
cryptshield-1.1.1.dist-info/METADATA
cryptshield-1.1.1.dist-info/WHEEL
cryptshield-1.1.1.dist-info/entry_points.txt
cryptshield-1.1.1.dist-info/top_level.txt
cryptshield-1.1.1.dist-info/RECORD
