Metadata-Version: 2.4
Name: cryptshield
Version: 1.1.1
Summary: Secure Encryption and Deletion Application
Author: Wilmer Martinez
License: MIT License
Project-URL: Homepage, https://github.com/wilmerm/cryptshield
Project-URL: Documentation, https://github.com/wilmerm/cryptshield?tab=readme-ov-file#secure-encryption-and-deletion-application
Project-URL: Repository, https://github.com/wilmerm/cryptshield
Project-URL: Issues, https://github.com/wilmerm/cryptshield/issues
Project-URL: Release, https://github.com/wilmerm/cryptshield/releases
Keywords: encryption,deletion,secure,application,python,cryptography,cryptshield,guardian,privacy,security,file,folder,data,protection,safety,safeguard,lock,unlock,erase,wipe,shred,scrub,clean,destroy,confidential,sensitive,information,safekeeping,cybersecurity
Classifier: Development Status :: 5 - Production/Stable
Classifier: Intended Audience :: Developers
Classifier: Topic :: Security :: Cryptography
Classifier: License :: OSI Approved :: MIT License
Classifier: Natural Language :: English
Classifier: Natural Language :: Spanish
Classifier: Programming Language :: Python
Classifier: Programming Language :: Python :: 3.10
Classifier: Programming Language :: Python :: 3.11
Classifier: Programming Language :: Python :: 3.12
Classifier: Programming Language :: Python :: 3.13
Requires-Python: >=3.10
License-File: LICENSE
Requires-Dist: cryptography
Requires-Dist: Pillow
Dynamic: license-file
